module_tp/__init__.py
module_tp/module_tp.py
module_tp-1.0.1.dist-info/LICENSE.txt
module_tp-1.0.1.dist-info/METADATA
module_tp-1.0.1.dist-info/WHEEL
module_tp-1.0.1.dist-info/top_level.txt
module_tp-1.0.1.dist-info/RECORD
