Metadata-Version: 2.1
Name: module_tp
Version: 1.0.1
Summary: An awesome package that does something
Home-page: http://pypi.python.org/pypi/package_tp/
Author: youli
Author-email: y.meflah@esi-sba.dz
License: LICENSE.txt
License-File: LICENSE.txt
